sicoob/__init__.py
sicoob/api_client.py
sicoob/async_boleto.py
sicoob/async_cache.py
sicoob/async_client.py
sicoob/async_pix.py
sicoob/boleto.py
sicoob/cache.py
sicoob/client.py
sicoob/cobranca.py
sicoob/config.py
sicoob/constants.py
sicoob/conta_corrente.py
sicoob/debug.py
sicoob/exceptions.py
sicoob/logging_config.py
sicoob/pagination.py
sicoob/pix.py
sicoob/resilience.py
sicoob/validation.py
sicoob/auth/__init__.py
sicoob/auth/oauth.py
tests/__init__.py
tests/conftest.py
tests/test_api_client.py
tests/test_async_boleto.py
tests/test_async_cache.py
tests/test_async_client_advanced.py
tests/test_async_client_certificate.py
tests/test_async_client_errors.py
tests/test_async_client_retry.py
tests/test_async_client_simple.py
tests/test_async_pix.py
tests/test_async_rate_limiting.py
tests/test_auth.py
tests/test_boleto.py
tests/test_boleto_integracao.py
tests/test_cache.py
tests/test_certificado_producao.py
tests/test_client.py
tests/test_config.py
tests/test_constants.py
tests/test_conta_corrente.py
tests/test_conta_corrente_integracao.py
tests/test_debug.py
tests/test_exceptions.py
tests/test_logging.py
tests/test_pagination.py
tests/test_pix.py
tests/test_pix_integracao.py
tests/test_resilience.py
tests/test_validation.py
sicoob_sdk-0.2.14.dist-info/METADATA
sicoob_sdk-0.2.14.dist-info/WHEEL
sicoob_sdk-0.2.14.dist-info/top_level.txt
sicoob_sdk-0.2.14.dist-info/RECORD
