Metadata-Version: 2.4
Name: sicoob-sdk
Version: 0.2.14
Summary: A Python SDK for Sicoob API
Author-email: Fábio Thomaz <fabio@ladder.dev.br>
License-Expression: MIT
Classifier: Development Status :: 3 - Alpha
Classifier: Intended Audience :: Developers
Classifier: Programming Language :: Python :: 3
Classifier: Programming Language :: Python :: 3.10
Classifier: Programming Language :: Python :: 3.11
Classifier: Programming Language :: Python :: 3.12
Requires-Python: >=3.10
Requires-Dist: requests>=2.25.1
Requires-Dist: python-dotenv>=0.15.0
Requires-Dist: requests-pkcs12>=1.25
Requires-Dist: pypix-api==0.8.0
Requires-Dist: aiohttp>=3.8.0
Requires-Dist: aiofiles>=24.0.0
Requires-Dist: pytest-asyncio>=1.1.0
Requires-Dist: cryptography>=41.0.0
Provides-Extra: dev
Requires-Dist: pytest>=7.0.0; extra == "dev"
Requires-Dist: pytest-mock>=3.6.1; extra == "dev"
Requires-Dist: build>=1.2.2.post1; extra == "dev"
Requires-Dist: twine>=6.1.0; extra == "dev"
Requires-Dist: ruff>=0.4.2; extra == "dev"
